README.md
setup.py
datomizer/__init__.py
datomizer/datogenerator.py
datomizer/datomapper.py
datomizer/datomizer.py
datomizer/datotrainer.py
datomizer.egg-info/PKG-INFO
datomizer.egg-info/SOURCES.txt
datomizer.egg-info/dependency_links.txt
datomizer.egg-info/requires.txt
datomizer.egg-info/top_level.txt
datomizer/helpers/common_helper.py
datomizer/helpers/authentication/authentication_helper.py
datomizer/helpers/autodiscovery/autodiscovery_helper.py
datomizer/helpers/business_unit_project/business_unit_project_helper.py
datomizer/helpers/datasource/datasource_helper.py
datomizer/helpers/generator/generator_helper.py
datomizer/helpers/train/train_helper.py
datomizer/source/conf.py
datomizer/utils/constants.py
datomizer/utils/general.py
datomizer/utils/step_types.py