Metadata-Version: 2.1
Name: datomizer
Version: 0.0.11
Summary: Datomize python client
Home-page: https://datomize.github.io/datomizeSDK
Author: Liron Cohen
Author-email: liron.cohen@datomize.com
License: UNKNOWN
Project-URL: Documentation, https://datomize.github.io/datomizeSDK
Platform: UNKNOWN
